structflow/__init__.py
structflow/document.py
structflow/py.typed
structflow/tags/__init__.py
structflow/tags/base.py
structflow/tags/edits.py
structflow/tags/embedded.py
structflow/tags/forms.py
structflow/tags/grouping.py
structflow/tags/head.py
structflow/tags/links.py
structflow/tags/scripting.py
structflow/tags/sections.py
structflow/tags/table.py
structflow/tags/text.py
structflow/tags/types.py
structflow-3.0.1.dist-info/WHEEL
structflow-3.0.1.dist-info/METADATA
structflow-3.0.1.dist-info/RECORD
