Metadata-Version: 2.4
Name: structflow
Version: 3.0.1
Summary: A Python library for programmatic HTML generation with type safety and a clean API
Keywords: html,generation,web,markup,template,type-safe
Author: Pedro José Mora Gallegos
Author-email: Pedro José Mora Gallegos <pedrojosemoragallegos@outlook.de>
License-Expression: MIT
Classifier: Development Status :: 5 - Production/Stable
Classifier: Intended Audience :: Developers
Classifier: License :: OSI Approved :: MIT License
Classifier: Operating System :: OS Independent
Classifier: Programming Language :: Python :: 3
Classifier: Programming Language :: Python :: 3.10
Classifier: Programming Language :: Python :: 3.11
Classifier: Programming Language :: Python :: 3.12
Classifier: Programming Language :: Python :: 3.13
Classifier: Topic :: Internet :: WWW/HTTP :: Dynamic Content
Classifier: Topic :: Software Development :: Libraries :: Python Modules
Classifier: Topic :: Text Processing :: Markup :: HTML
Classifier: Topic :: Software Development :: Code Generators
Classifier: Typing :: Typed
Requires-Python: >=3.10, <3.14
Project-URL: Homepage, https://github.com/pedrojosemoragallegos/structflow
Project-URL: Repository, https://github.com/pedrojosemoragallegos/structflow
